README.rst
setup.cfg
setup.py
switchio/__init__.py
switchio/api.py
switchio/cli.py
switchio/commands.py
switchio/connection.py
switchio/distribute.py
switchio/handlers.py
switchio/loop.py
switchio/marks.py
switchio/models.py
switchio/protocol.py
switchio/serve.py
switchio/sync.py
switchio/utils.py
switchio.egg-info/PKG-INFO
switchio.egg-info/SOURCES.txt
switchio.egg-info/dependency_links.txt
switchio.egg-info/entry_points.txt
switchio.egg-info/requires.txt
switchio.egg-info/top_level.txt
switchio/../conf/switchiodp.xml
switchio/apps/__init__.py
switchio/apps/bert.py
switchio/apps/blockers.py
switchio/apps/call_gen.py
switchio/apps/dtmf.py
switchio/apps/players.py
switchio/apps/routers.py
switchio/apps/measure/__init__.py
switchio/apps/measure/cdr.py
switchio/apps/measure/mpl_helpers.py
switchio/apps/measure/shmarray.py
switchio/apps/measure/storage.py
switchio/apps/measure/sys.py