Metadata-Version: 1.1
Name: switchio
Version: 0.1.0a1
Summary: asyncio powered FreeSWITCH cluster control
Home-page: https://github.com/friends-of-freeswitch/switchio
Author: Tyler Goodlet
Author-email: tgoodlet@gmail.com
License: Mozilla
Platform: linux
Classifier: Development Status :: 3 - Alpha
Classifier: License :: OSI Approved :: Mozilla Public License 2.0 (MPL 2.0)
Classifier: Operating System :: POSIX :: Linux
Classifier: Programming Language :: Python :: 3.5
Classifier: Programming Language :: Python :: 3.6
Classifier: Intended Audience :: Telecommunications Industry
Classifier: Intended Audience :: Developers
Classifier: Topic :: Communications :: Telephony
Classifier: Topic :: Software Development :: Testing :: Traffic Generation
Classifier: Topic :: System :: Clustering
Classifier: Environment :: Console
